pet/__init__.py
pet/that.py
pet/data/__init__.py
pet/data/generator.py
pet/data/ip_address.xlsx
pet/data/ip_address.xlsx.py
pet/data/st.py
pet/data/st.xlsx
pet/data/st.xlsx.py
pet/data/subway.xlsx
pet/data/subway.xlsx.py
pet/textbook1/__init__.py
python_teaching_tools-0.2.3.dist-info/METADATA
python_teaching_tools-0.2.3.dist-info/WHEEL
python_teaching_tools-0.2.3.dist-info/top_level.txt
python_teaching_tools-0.2.3.dist-info/RECORD
