Metadata-Version: 2.1
Name: python-teaching-tools
Version: 0.2.3
Summary: Python Education Tools for Teaching
Home-page: https://github.com/liluqun
Author: Prof.Luqun Li
Author-email: liluqun@gmail.com
Project-URL: Bug Tracker, https://github.com/liluqun
Classifier: Programming Language :: Python :: 3
Classifier: License :: OSI Approved :: MIT License
Classifier: Operating System :: OS Independent
Requires-Python: >=3.6
